[
  {
    "id": "c2296485-6c79-4e53-8bc3-3e817aa82a35",
    "name": "tret",
    "phone": "erttertre",
    "workType": "বীজ বপন",
    "date": "27/11/2025",
    "hours": 5.0,
    "ratePerHour": 122.0,
    "totalAmount": 610.0,
    "paymentStatus": "বাকি আছে",
    "notes": "rere"
  },
  {
    "id": "95d1300f-bde0-421c-8f67-a2718c385be9",
    "name": "Abin",
    "phone": "21143143",
    "workType": "বীজ বপন",
    "date": "26/11/2025",
    "hours": 12.0,
    "ratePerHour": 122.0,
    "totalAmount": 1464.0,
    "paymentStatus": "completed",
    "notes": "32432"
  }
]